mc/__init__.py
mc/_mcbase.py
mc/test.py
mc/data/AAPL.csv
mc/data/MBSComtrade.csv
mc/data/MSFT.csv
mc/data/__init__.py
mc/data/dow_jones_index.csv
mc/distributions/__init__.py
mc/distributions/_benford.py
mc/distributions/_binom.py
mc/distributions/_chisq.py
mc/distributions/_exponential.py
mc/distributions/_f.py
mc/distributions/_poisson.py
mc/distributions/_student.py
mc/distributions/_zipf.py
mc/experiments/__init__.py
mc/experiments/_dices.py
mc/experiments/_galton_board.py
mc/experiments/_paper_clips.py
mc/experiments/_parcel.py
mc/experiments/_pi.py
mc/experiments/_prisoners.py
mc/experiments/_sudden_death.py
mc/gui/__init__.py
mc/samplings/__init__.py
mc/samplings/_anova.py
mc/samplings/_bartlett_sphericity_test.py
mc/samplings/_bartlett_test.py
mc/samplings/_chisq_gof_test.py
mc/samplings/_clt.py
mc/samplings/_cochrane_q_test.py
mc/samplings/_fk_test.py
mc/samplings/_hotelling_t2_test.py
mc/samplings/_kw_test.py
mc/samplings/_levene_test.py
mc/samplings/_median_test.py
mc/samplings/_sign_test.py
mc/samplings/_t_test.py
mc_tk-1.0.2.dist-info/LICENSE
mc_tk-1.0.2.dist-info/METADATA
mc_tk-1.0.2.dist-info/WHEEL
mc_tk-1.0.2.dist-info/top_level.txt
mc_tk-1.0.2.dist-info/RECORD
